pythonwhois/__init__.py
pythonwhois/airports.dat
pythonwhois/countries.dat
pythonwhois/countries3.dat
pythonwhois/net.py
pythonwhois/parse.py
pythonwhois/shared.py
pythonwhois/states_au.dat
pythonwhois/states_ca.dat
pythonwhois/states_us.dat
pythonwhois2-2.5.3.data/scripts/pwhois
pythonwhois2-2.5.3.dist-info/licenses/LICENSE.txt
pythonwhois2-2.5.3.dist-info/METADATA
pythonwhois2-2.5.3.dist-info/WHEEL
pythonwhois2-2.5.3.dist-info/top_level.txt
pythonwhois2-2.5.3.dist-info/RECORD
