Metadata-Version: 2.4
Name: pythonwhois2
Version: 2.5.3
Summary: Module for retrieving and parsing the WHOIS data for a domain. Supports most domains. No dependencies.
Home-page: http://github.com/froztty/pythonwhois2
Author: Nathan Nguyen
Author-email: nathannn702@gmail.com
License: WTFPL
Provides: pythonwhois
License-File: LICENSE.txt
Requires-Dist: argparse
Dynamic: author
Dynamic: author-email
Dynamic: home-page
Dynamic: license
Dynamic: license-file
Dynamic: provides
Dynamic: requires-dist
Dynamic: summary
